{
    "filterGroups": [
        {
            "file": "lsq_filter_Leica_1.gfilter",
            "valid_key": "4a32e5610712b947",
            "name": "lsq_filter_group_Leica",
            "default_filter_id": 12,
            "color": "#E74C3C",
            "filters": [
                {
                    "id": 11,
                    "name": "lsq_filter_Brilliant",
                    "thumb": "lsq_filter_thumb_Brilliant",
                    "color": "#E74C3C",
                    "args": {
                        "mixied": 0.5
                    }
                },
                { "id": 12, "name": "lsq_filter_Leica", "args": { "mixied": 0.6 } },
                { "id": 13, "name": "lsq_filter_Gloss", "args": { "mixied": 0.55 } },
                { "id": 14, "name": "lsq_filter_Harmony", "args": { "mixied": 0.75 } },
                { "id": 15, "name": "lsq_filter_Noir" }
            ]
        },
        {
            "file": "lsq_filter_Magic_7.gfilter",
            "valid_key": "10a7fa8557837a5c",
            "name": "lsq_filter_group_Magic",
            "default_filter_id": 72,
            "filters": [
                { "id": 71, "name": "lsq_filter_MagicRed" },
                { "id": 72, "name": "lsq_filter_MagicYellow" },
                { "id": 73, "name": "lsq_filter_MagicBlue" },
                { "id": 74, "name": "lsq_filter_MagicGreen" },
                { "id": 75, "name": "lsq_filter_MagicPurple" }
            ]
        },
        {
            "file": "lsq_filter_Beauty_6.gfilter",
            "valid_key": "4b2493145477da42",
            "name": "lsq_filter_group_Beauty",
            "default_filter_id": 65,
            "filters": [
                { "id": 61, "name": "lsq_filter_SkinNature", "args": { "smoothing": 0.4 } },
                { "id": 62, "name": "lsq_filter_SkinPink", "args": { "smoothing": 0.4, "mixied": 0.55 } },
                { "id": 63, "name": "lsq_filter_SkinJelly", "args": { "smoothing": 0.4, "mixied": 0.45 } },
                { "id": 64, "name": "lsq_filter_SkinNoir", "args": { "smoothing": 0.4, "mixied": 1.0 } },
                { "id": 65, "name": "lsq_filter_SkinRuddy", "args": { "smoothing": 0.4, "mixied": 0.45 } },
                { "id": 66, "name": "lsq_filter_SkinSugar", "args": { "smoothing": 0.4, "mixied": 0.5 } },
                { "id": 67, "name": "lsq_filter_SkinPowder", "args": { "smoothing": 0.4, "mixied": 0.6 } }
            ]
        },
        {
            "file": "lsq_filter_Lomo_2.gfilter",
            "valid_key": "62d9fd597a0e2d9d",
            "name": "lsq_filter_group_Lomo",
            "default_filter_id": 24,
            "filters": [
                { "id": 21, "name": "lsq_filter_Lomo", "args": { "mixied": 0.6 } },
                { "id": 22, "name": "lsq_filter_Clear", "args": { "mixied": 0.6 } },
                { "id": 23, "name": "lsq_filter_Morning", "args": { "mixied": 0.75 } },
                { "id": 24, "name": "lsq_filter_Newborn", "args": { "mixied": 0.7 } },
                { "id": 25, "name": "lsq_filter_Artistic", "args": { "mixied": 0.7 } }
            ]
        },
        {
            "file": "lsq_filter_Food_3.gfilter",
            "valid_key": "9841530ac0eb74d8",
            "name": "lsq_filter_group_Food",
            "default_filter_id": 32,
            "filters": [
                { "id": 31, "name": "lsq_filter_Abao", "args": { "mixied": 0.7 } },
                { "id": 32, "name": "lsq_filter_Thick", "args": { "mixied": 0.65 } },
                { "id": 33, "name": "lsq_filter_Vintage", "args": { "mixied": 0.7 } },
                { "id": 34, "name": "lsq_filter_Nostalgic", "args": { "mixied": 0.65 } },
                { "id": 35, "name": "lsq_filter_Forest", "args": { "mixied": 0.45 } }
            ]
        },
        {
            "file": "lsq_filter_Enhance_4.gfilter",
            "valid_key": "1ece1ddf404b6f19",
            "name": "lsq_filter_group_Enhance",
            "default_filter_id": 45,
            "filters": [
                { "id": 41, "name": "lsq_filter_Cheerful", "args": { "mixied": 0.75 } },
                { "id": 42, "name": "lsq_filter_Lightup", "args": { "mixied": 0.85 } },
                { "id": 43, "name": "lsq_filter_Relaxed", "args": { "mixied": 0.6 } },
                { "id": 44, "name": "lsq_filter_Rough", "args": { "mixied": 0.55 } },
                { "id": 45, "name": "lsq_filter_Instant", "args": { "mixied": 0.5 } }
            ]
        },
        {
            "file": "lsq_filter_Glare_5.gfilter",
            "valid_key": "e76ac25737f771e6",
            "name": "lsq_filter_group_Glare",
            "default_filter_id": 57,
            "filters": [
                {
                    "id": 51,
                    "name": "lsq_filter_Wintersunshine",
                    "args": {
                        "mixied": 0.8
                    }
                 },
                { "id": 52, "name": "lsq_filter_Coloration" },
                { "id": 53, "name": "lsq_filter_Fluorescent" },
                { "id": 54, "name": "lsq_filter_Freshmorning" },
                { "id": 55, "name": "lsq_filter_Holidaysunshine" },
                { "id": 56, "name": "lsq_filter_Purplemoon" },
                { "id": 57, "name": "lsq_filter_Summersunshine" }
            ]
        }
    ],
    "stickerCategories": [
        { "id": 1, "name": "lsq_sticker_cate_default" },
        { "id": 2, "name": "lsq_sticker_cate_mood" },
        { "id": 3, "name": "lsq_sticker_cate_watermark" }
    ],
    "stickerGroups": [
        {
            "file": "lsq_sticker_1_257.gsce",
            "valid_key": "2935bc45d866c391",
            "name": "lsq_sticker_1_1",
            "stickers": [
                { "id": 1613 },
                { "id": 1614 },
                { "id": 1615 },
                { "id": 1616 },
                { "id": 1617 },
                { "id": 1618 },
                { "id": 1619 },
                {
                    "id": 1620,
                    "width": 100,
                    "height": 100,
                    "texts": [
                        {
                            "id": 201,
                            "content": "lsq_sticker_text_1_1_1_1",
                            "color": "#FFFFFF"
                        }
                    ]
                }
            ]
        },
        { "file": "lsq_sticker_2_249.gsce", "valid_key": "69b180a2c62b8686" },
        { "file": "lsq_sticker_3_250.gsce", "valid_key": "0a39c15b64255477" }
    ]
}